npr/__init__.py
npr/api/helpers.py
npr/api/server.py
npr/api/state.py
npr/api/migrations/__init__.py
npr/api/migrations/migrator.py
npr/api/migrations/v0_1_1.py
npr/cli/__init__.py
npr/cli/controller.py
npr/cli/handlers/__init__.py
npr/cli/handlers/dispatcher.py
npr/cli/handlers/search.py
npr/domain/__init__.py
npr/domain/action.py
npr/domain/constants.py
npr/domain/exceptions.py
npr/domain/player.py
npr/domain/station.py
npr/domain/stream.py
npr/services/backend.py
npr/services/npr.py
npr_cli-0.1.3.dist-info/METADATA
npr_cli-0.1.3.dist-info/WHEEL
npr_cli-0.1.3.dist-info/entry_points.txt
npr_cli-0.1.3.dist-info/top_level.txt
npr_cli-0.1.3.dist-info/RECORD
