Metadata-Version: 2.1
Name: npr-cli
Version: 0.1.3
Summary: A simple npr streaming cli
Author-email: evanmags <magnussen.evan@gmail.com>
Project-URL: homepage, https://github.com/evanmags/npr-cli
Project-URL: repository, https://github.com/evanmags/npr-cli
Classifier: Environment :: Console
Classifier: License :: OSI Approved :: MIT License
Classifier: Operating System :: MacOS
Classifier: Programming Language :: Python :: 3.10
Classifier: Topic :: Multimedia :: Sound/Audio :: Players
Requires-Python: >=3.10
Requires-Dist: click
Requires-Dist: flask
Requires-Dist: gunicorn
Requires-Dist: inquirerpy
Requires-Dist: packaging
Requires-Dist: python-vlc
Requires-Dist: requests
